<dir>
    <title>Sarah</title>
    <fxxxmovies>fxmtag/sarah</fxxxmovies>
</dir>

<dir>
    <title>Sarah Banks</title>
    <fxxxmovies>fxmtag/sarah-banks</fxxxmovies>
</dir>

<dir>
    <title>Sarah Blue</title>
    <fxxxmovies>fxmtag/sarah-blue</fxxxmovies>
</dir>

<dir>
    <title>Sarah Dark</title>
    <fxxxmovies>fxmtag/sarah-dark</fxxxmovies>
</dir>

<dir>
    <title>Sarah James</title>
    <fxxxmovies>fxmtag/sarah-james</fxxxmovies>
</dir>

<dir>
    <title>Sarah Jane Hamilton</title>
    <fxxxmovies>fxmtag/sarah-jane-hamilton</fxxxmovies>
</dir>

<dir>
    <title>Sarah Jessie</title>
    <fxxxmovies>fxmtag/sarah-jessie</fxxxmovies>
</dir>

<dir>
    <title>Sarah Shevon</title>
    <fxxxmovies>fxmtag/sarah-shevon</fxxxmovies>
</dir>

<dir>
    <title>Sarah Twain</title>
    <fxxxmovies>fxmtag/sarah-twain</fxxxmovies>
</dir>

<dir>
    <title>Sarah Vandella</title>
    <fxxxmovies>fxmtag/sarah-vandella</fxxxmovies>
</dir>

<dir>
    <title>Sarah Young</title>
    <fxxxmovies>fxmtag/sarah-young</fxxxmovies>
</dir>

<dir>
    <title>Sascha</title>
    <fxxxmovies>fxmtag/sascha</fxxxmovies>
</dir>

<dir>
    <title>Sasha</title>
    <fxxxmovies>fxmtag/sasha</fxxxmovies>
</dir>

<dir>
    <title>Sasha Gabor</title>
    <fxxxmovies>fxmtag/sasha-gabor</fxxxmovies>
</dir>

<dir>
    <title>Sasha Grey</title>
    <fxxxmovies>fxmtag/sasha-grey</fxxxmovies>
</dir>

<dir>
    <title>Sasha Heart</title>
    <fxxxmovies>fxmtag/sasha-heart</fxxxmovies>
</dir>

<dir>
    <title>Sasha Knox</title>
    <fxxxmovies>fxmtag/sasha-knox</fxxxmovies>
</dir>

<dir>
    <title>Sasha Rose</title>
    <fxxxmovies>fxmtag/sasha-rose</fxxxmovies>
</dir>

<dir>
    <title>Saskia</title>
    <fxxxmovies>fxmtag/saskia</fxxxmovies>
</dir>

<dir>
    <title>Saskia Farell</title>
    <fxxxmovies>fxmtag/saskia-farell</fxxxmovies>
</dir>

<dir>
    <title>Satin Bloom</title>
    <fxxxmovies>fxmtag/satin-bloom</fxxxmovies>
</dir>

<dir>
    <title>Satine Phoenix</title>
    <fxxxmovies>fxmtag/satine-phoenix</fxxxmovies>
</dir>

<dir>
    <title>Sativa Rose</title>
    <fxxxmovies>fxmtag/sativa-rose</fxxxmovies>
</dir>

<dir>
    <title>Savana Styles</title>
    <fxxxmovies>fxmtag/savana-styles</fxxxmovies>
</dir>

<dir>
    <title>Savanna Samson</title>
    <fxxxmovies>fxmtag/savanna-samson</fxxxmovies>
</dir>

<dir>
    <title>Savannah</title>
    <fxxxmovies>fxmtag/savannah</fxxxmovies>
</dir>

<dir>
    <title>Savannah Fox</title>
    <fxxxmovies>fxmtag/savannah-fox</fxxxmovies>
</dir>

<dir>
    <title>Savannah Secret</title>
    <fxxxmovies>fxmtag/savannah-secret</fxxxmovies>
</dir>

<dir>
    <title>Savannah Stern</title>
    <fxxxmovies>fxmtag/savannah-stern</fxxxmovies>
</dir>

<dir>
    <title>Saya Song</title>
    <fxxxmovies>fxmtag/saya-song</fxxxmovies>
</dir>

<dir>
    <title>Scala</title>
    <fxxxmovies>fxmtag/scala</fxxxmovies>
</dir>

<dir>
    <title>Scarlet</title>
    <fxxxmovies>fxmtag/scarlet</fxxxmovies>
</dir>

<dir>
    <title>Scarlet Lavey</title>
    <fxxxmovies>fxmtag/scarlet-lavey</fxxxmovies>
</dir>

<dir>
    <title>Scarlet Red</title>
    <fxxxmovies>fxmtag/scarlet-red</fxxxmovies>
</dir>

<dir>
    <title>Scarlett</title>
    <fxxxmovies>fxmtag/scarlett</fxxxmovies>
</dir>

<dir>
    <title>Scarlett Pain</title>
    <fxxxmovies>fxmtag/scarlett-pain</fxxxmovies>
</dir>

<dir>
    <title>Scarlett Sage</title>
    <fxxxmovies>fxmtag/scarlett-sage</fxxxmovies>
</dir>

<dir>
    <title>scat</title>
    <fxxxmovies>fxmtag/scat</fxxxmovies>
</dir>

<dir>
    <title>Schl\u00e4uche</title>
    <fxxxmovies>fxmtag/schlauche</fxxxmovies>
</dir>

<dir>
    <title>School Girl</title>
    <fxxxmovies>fxmtag/school-girl</fxxxmovies>
</dir>

<dir>
    <title>Schoolgirl</title>
    <fxxxmovies>fxmtag/schoolgirl</fxxxmovies>
</dir>

<dir>
    <title>Schoolgirls</title>
    <fxxxmovies>fxmtag/schoolgirls</fxxxmovies>
</dir>

<dir>
    <title>Schwanger</title>
    <fxxxmovies>fxmtag/schwanger</fxxxmovies>
</dir>

<dir>
    <title>Schwester</title>
    <fxxxmovies>fxmtag/schwester</fxxxmovies>
</dir>

<dir>
    <title>Scissor Lock</title>
    <fxxxmovies>fxmtag/scissor-lock</fxxxmovies>
</dir>

<dir>
    <title>Scissor Locks</title>
    <fxxxmovies>fxmtag/scissor-locks</fxxxmovies>
</dir>

<dir>
    <title>Score</title>
    <fxxxmovies>fxmtag/score</fxxxmovies>
</dir>

<dir>
    <title>Scorpio</title>
    <fxxxmovies>fxmtag/scorpio</fxxxmovies>
</dir>

<dir>
    <title>Scott Irish</title>
    <fxxxmovies>fxmtag/scott-irish</fxxxmovies>
</dir>

<dir>
    <title>Scott Lyons</title>
    <fxxxmovies>fxmtag/scott-lyons</fxxxmovies>
</dir>

<dir>
    <title>Scott Nails</title>
    <fxxxmovies>fxmtag/scott-nails</fxxxmovies>
</dir>

<dir>
    <title>SCREW MY WIFE PRODUCTIONS</title>
    <fxxxmovies>fxmtag/screw-my-wife-productions</fxxxmovies>
</dir>

<dir>
    <title>SD</title>
    <fxxxmovies>fxmtag/sd</fxxxmovies>
</dir>

<dir>
    <title>Sean Michaels</title>
    <fxxxmovies>fxmtag/sean-michaels</fxxxmovies>
</dir>

<dir>
    <title>Sean Rider</title>
    <fxxxmovies>fxmtag/sean-rider</fxxxmovies>
</dir>

<dir>
    <title>Sebastian Barrio</title>
    <fxxxmovies>fxmtag/sebastian-barrio</fxxxmovies>
</dir>

<dir>
    <title>Sebastien Barrio</title>
    <fxxxmovies>fxmtag/sebastien-barrio</fxxxmovies>
</dir>

<dir>
    <title>Seka</title>
    <fxxxmovies>fxmtag/seka</fxxxmovies>
</dir>

<dir>
    <title>Selen</title>
    <fxxxmovies>fxmtag/selen</fxxxmovies>
</dir>

<dir>
    <title>Selena</title>
    <fxxxmovies>fxmtag/selena</fxxxmovies>
</dir>

<dir>
    <title>Selena Rose</title>
    <fxxxmovies>fxmtag/selena-rose</fxxxmovies>
</dir>

<dir>
    <title>Selena Santana</title>
    <fxxxmovies>fxmtag/selena-santana</fxxxmovies>
</dir>

<dir>
    <title>Selena Silver</title>
    <fxxxmovies>fxmtag/selena-silver</fxxxmovies>
</dir>

<dir>
    <title>Selma Sins</title>
    <fxxxmovies>fxmtag/selma-sins</fxxxmovies>
</dir>