<dir>
    <title>Sensational Video</title>
    <fxxxmovies>fxmtag/sensational-video</fxxxmovies>
</dir>

<dir>
    <title>Sensi Pearl</title>
    <fxxxmovies>fxmtag/sensi-pearl</fxxxmovies>
</dir>

<dir>
    <title>Sensual Jane</title>
    <fxxxmovies>fxmtag/sensual-jane</fxxxmovies>
</dir>

<dir>
    <title>Serena</title>
    <fxxxmovies>fxmtag/serena</fxxxmovies>
</dir>

<dir>
    <title>Serena Ali</title>
    <fxxxmovies>fxmtag/serena-ali</fxxxmovies>
</dir>

<dir>
    <title>Serenity</title>
    <fxxxmovies>fxmtag/serenity</fxxxmovies>
</dir>

<dir>
    <title>Sergio</title>
    <fxxxmovies>fxmtag/sergio</fxxxmovies>
</dir>

<dir>
    <title>Seth Dickens</title>
    <fxxxmovies>fxmtag/seth-dickens</fxxxmovies>
</dir>

<dir>
    <title>Seth Gamble</title>
    <fxxxmovies>fxmtag/seth-gamble</fxxxmovies>
</dir>

<dir>
    <title>Seth Strong</title>
    <fxxxmovies>fxmtag/seth-strong</fxxxmovies>
</dir>

<dir>
    <title>Sevanteen</title>
    <fxxxmovies>fxmtag/sevanteen</fxxxmovies>
</dir>

<dir>
    <title>SevenTeen</title>
    <fxxxmovies>fxmtag/seventeen</fxxxmovies>
</dir>

<dir>
    <title>Sex</title>
    <fxxxmovies>fxmtag/sex</fxxxmovies>
</dir>

<dir>
    <title>Sex Impact</title>
    <fxxxmovies>fxmtag/sex-impact</fxxxmovies>
</dir>

<dir>
    <title>Sex Toy</title>
    <fxxxmovies>fxmtag/sex-toy</fxxxmovies>
</dir>

<dir>
    <title>Sex Toy Play</title>
    <fxxxmovies>fxmtag/sex-toy-play</fxxxmovies>
</dir>

<dir>
    <title>Sex Toys</title>
    <fxxxmovies>fxmtag/sex-toys</fxxxmovies>
</dir>

<dir>
    <title>Sexy</title>
    <fxxxmovies>fxmtag/sexy</fxxxmovies>
</dir>

<dir>
    <title>Sexy Cora</title>
    <fxxxmovies>fxmtag/sexy-cora</fxxxmovies>
</dir>

<dir>
    <title>Sexy Luna</title>
    <fxxxmovies>fxmtag/sexy-luna</fxxxmovies>
</dir>

<dir>
    <title>Sexy Susi</title>
    <fxxxmovies>fxmtag/sexy-susi</fxxxmovies>
</dir>

<dir>
    <title>Sexy Vanessa</title>
    <fxxxmovies>fxmtag/sexy-vanessa</fxxxmovies>
</dir>

<dir>
    <title>Seymore Butts</title>
    <fxxxmovies>fxmtag/seymore-butts</fxxxmovies>
</dir>

<dir>
    <title>Shadow</title>
    <fxxxmovies>fxmtag/shadow</fxxxmovies>
</dir>

<dir>
    <title>Shae Snow</title>
    <fxxxmovies>fxmtag/shae-snow</fxxxmovies>
</dir>

<dir>
    <title>Shae Summers</title>
    <fxxxmovies>fxmtag/shae-summers</fxxxmovies>
</dir>

<dir>
    <title>Shalina Devine</title>
    <fxxxmovies>fxmtag/shalina-devine</fxxxmovies>
</dir>

<dir>
    <title>Shana Lane</title>
    <fxxxmovies>fxmtag/shana-lane</fxxxmovies>
</dir>

<dir>
    <title>Shane</title>
    <fxxxmovies>fxmtag/shane</fxxxmovies>
</dir>

<dir>
    <title>Shane Diesel</title>
    <fxxxmovies>fxmtag/shane-diesel</fxxxmovies>
</dir>

<dir>
    <title>Shanna Mccullough</title>
    <fxxxmovies>fxmtag/shanna-mccullough</fxxxmovies>
</dir>

<dir>
    <title>Shannon</title>
    <fxxxmovies>fxmtag/shannon</fxxxmovies>
</dir>

<dir>
    <title>Shannon Kelly</title>
    <fxxxmovies>fxmtag/shannon-kelly</fxxxmovies>
</dir>

<dir>
    <title>Shannya Tweeks</title>
    <fxxxmovies>fxmtag/shannya-tweeks</fxxxmovies>
</dir>

<dir>
    <title>share-online.biz</title>
    <fxxxmovies>fxmtag/share-online-biz</fxxxmovies>
</dir>

<dir>
    <title>share-online Porn</title>
    <fxxxmovies>fxmtag/share-online-porn</fxxxmovies>
</dir>

<dir>
    <title>Sharka Blue</title>
    <fxxxmovies>fxmtag/sharka-blue</fxxxmovies>
</dir>

<dir>
    <title>Sharon</title>
    <fxxxmovies>fxmtag/sharon</fxxxmovies>
</dir>

<dir>
    <title>Sharon Da Vale</title>
    <fxxxmovies>fxmtag/sharon-da-vale</fxxxmovies>
</dir>

<dir>
    <title>Sharon Kane</title>
    <fxxxmovies>fxmtag/sharon-kane</fxxxmovies>
</dir>

<dir>
    <title>Sharon Lee</title>
    <fxxxmovies>fxmtag/sharon-lee</fxxxmovies>
</dir>

<dir>
    <title>Sharon Mitchell</title>
    <fxxxmovies>fxmtag/sharon-mitchell</fxxxmovies>
</dir>

<dir>
    <title>Sharon Pink</title>
    <fxxxmovies>fxmtag/sharon-pink</fxxxmovies>
</dir>

<dir>
    <title>Sharon Thorpe</title>
    <fxxxmovies>fxmtag/sharon-thorpe</fxxxmovies>
</dir>

<dir>
    <title>Sharon Wild</title>
    <fxxxmovies>fxmtag/sharon-wild</fxxxmovies>
</dir>

<dir>
    <title>Shauna Grant</title>
    <fxxxmovies>fxmtag/shauna-grant</fxxxmovies>
</dir>

<dir>
    <title>Shaved</title>
    <fxxxmovies>fxmtag/shaved</fxxxmovies>
</dir>

<dir>
    <title>Shaved Pussy</title>
    <fxxxmovies>fxmtag/shaved-pussy</fxxxmovies>
</dir>

<dir>
    <title>Shawna Lenee</title>
    <fxxxmovies>fxmtag/shawna-lenee</fxxxmovies>
</dir>

<dir>
    <title>Shawnee Cates</title>
    <fxxxmovies>fxmtag/shawnee-cates</fxxxmovies>
</dir>

<dir>
    <title>Shay Fox</title>
    <fxxxmovies>fxmtag/shay-fox</fxxxmovies>
</dir>

<dir>
    <title>Shay Jordan</title>
    <fxxxmovies>fxmtag/shay-jordan</fxxxmovies>
</dir>

<dir>
    <title>Shay Sweet</title>
    <fxxxmovies>fxmtag/shay-sweet</fxxxmovies>
</dir>

<dir>
    <title>Shayla LaVeaux</title>
    <fxxxmovies>fxmtag/shayla-laveaux</fxxxmovies>
</dir>

<dir>
    <title>SHE-MALE</title>
    <fxxxmovies>fxmtag/she-male</fxxxmovies>
</dir>

<dir>
    <title>Sheena Rose</title>
    <fxxxmovies>fxmtag/sheena-rose</fxxxmovies>
</dir>

<dir>
    <title>Sheena Ryder</title>
    <fxxxmovies>fxmtag/sheena-ryder</fxxxmovies>
</dir>

<dir>
    <title>Sheena Shaw</title>
    <fxxxmovies>fxmtag/sheena-shaw</fxxxmovies>
</dir>

<dir>
    <title>Sheila</title>
    <fxxxmovies>fxmtag/sheila</fxxxmovies>
</dir>

<dir>
    <title>Sheila Grant</title>
    <fxxxmovies>fxmtag/sheila-grant</fxxxmovies>
</dir>

<dir>
    <title>Sheila Marie</title>
    <fxxxmovies>fxmtag/sheila-marie</fxxxmovies>
</dir>

<dir>
    <title>Shemale</title>
    <fxxxmovies>fxmtag/shemale</fxxxmovies>
</dir>

<dir>
    <title>Shemale Big Ass</title>
    <fxxxmovies>fxmtag/shemale-big-ass</fxxxmovies>
</dir>

<dir>
    <title>Shemale Hardcore</title>
    <fxxxmovies>fxmtag/shemale-hardcore</fxxxmovies>
</dir>